ui_mcp_server/__init__.py
ui_mcp_server/models.py
ui_mcp_server/py.typed
ui_mcp_server/server.py
ui_mcp_server-0.1.0.dist-info/METADATA
ui_mcp_server-0.1.0.dist-info/WHEEL
ui_mcp_server-0.1.0.dist-info/entry_points.txt
ui_mcp_server-0.1.0.dist-info/licenses/LICENSE.txt
ui_mcp_server-0.1.0.dist-info/RECORD
