Metadata-Version: 2.4
Name: ui-mcp-server
Version: 0.1.0
Summary: Add your description here
License-File: LICENSE.txt
Requires-Python: >=3.12
Requires-Dist: mcp[cli]>=1.12.2
